mlfields/__init__.py
mlfields/client.py
mlfields/enable_metrics.py
mlfields/evaluation_metrics.py
mlfields/feature_definitions.py
mlfields/feature_evaluations.py
mlfields/feature_evaluations_for_each_feature.py
mlfields/feature_matrices.py
mlfields/project.py
mlfields/apis/__init__.py
mlfields/apis/fds.py
mlfields/apis/fes.py
mlfields/apis/fms.py
mlfields/apis/metrics.py
mlfields/apis/metrics_in_use.py
mlfields/apis/pjs.py
mlfields/data_models/__init__.py
mlfields/static/style.css
mlfields/templates/base.html
mlfields/templates/feature_definitions/list.html
mlfields/templates/feature_evaluations/list.html
mlfields/templates/feature_evaluations/list_for_each_feature.html
mlfields/templates/feature_evaluations/list_metrics.html
mlfields/templates/feature_matrices/list.html
mlfields/templates/projects/create.html
mlfields/templates/projects/list.html
mlfields/templates/projects/project_base.html
mlfields/utils/__init__.py
mlfields/utils/initial_metrics.py
mlfields/utils/metrics_utils.py
mlfields-0.0.9.dist-info/METADATA
mlfields-0.0.9.dist-info/WHEEL
mlfields-0.0.9.dist-info/top_level.txt
mlfields-0.0.9.dist-info/RECORD
