Metadata-Version: 2.1
Name: mlfields
Version: 0.0.9
Summary: UI system to manage ML input
Home-page: https://github.com/not-so-fat/mlfields
Author: @not-so-fat
Author-email: conjurer.not.so.fat@gmail.com
License: UNKNOWN
Platform: UNKNOWN
Classifier: Programming Language :: Python :: 3
Classifier: License :: OSI Approved :: MIT License
Classifier: Operating System :: OS Independent
Requires-Python: >=3.6
Requires-Dist: flask
Requires-Dist: waitress
Requires-Dist: Flask-SQLAlchemy
Requires-Dist: flask-restful
Requires-Dist: pandas
Requires-Dist: numpy
Requires-Dist: scipy
Requires-Dist: scikit-learn
Requires-Dist: requests
